ctes_models_py/__init__.py
ctes_models_py/model.py
ctes_models_py/model.pyi
ctes_models_py-0.1.0.dist-info/licenses/LICENSE
ctes_models_py-0.1.0.dist-info/METADATA
ctes_models_py-0.1.0.dist-info/WHEEL
ctes_models_py-0.1.0.dist-info/top_level.txt
ctes_models_py-0.1.0.dist-info/RECORD
