Metadata-Version: 2.4
Name: ctes-models-py
Version: 0.1.0
Summary: A library for Ciphertext Ecosystem models.
Author-email: Rebase <rebased.again@gmail.com>
License-Expression: MIT
Classifier: Programming Language :: Python :: 3
Classifier: Operating System :: OS Independent
Requires-Python: >=3.9
License-File: LICENSE
Requires-Dist: protobuf>=6.33.4
Dynamic: license-file
